{
  "_id": "KPconjureshadowtitan",
  "flags": {},
  "type": "spell",
  "img": "icons/mystery-man.png",
  "name": "Conjure Shadow Titan",
  "permission": {
    "default": 0
  },
  "system": {
    "source": "DM,HH,DM:S",
    "prepared": false,
    "level": 7,
    "school": "con",
    "activation": {
      "type": "minute",
      "cost": "1",
      "condition": ""
    },
    "range": {
      "value": 90,
      "units": "ft"
    },
    "duration": {
      "value": 1,
      "units": "hour"
    },
    "components": {
      "value": "",
      "vocal": true,
      "somatic": true,
      "material": false,
      "ritual": false,
      "concentration": false
    },
    "materials": {
      "value": "",
      "consumed": false,
      "cost": 0,
      "supply": 0
    },
    "target": {
      "value": null,
      "units": "",
      "type": ""
    },
    "actionType": "util",
    "damage": {
      "parts": [],
      "versatile": ""
    },
    "save": {
      "ability": "",
      "dc": null
    },
    "description": {
      "value": "<p><em><strong>Deep Magic: </strong>shadow</em><br>You summon a shadow titan, which appears in an unoccupied space that you can see within range. The shadow titan's statistics are identical to a @Compendium[dnd5e.monsters.SOin81NWijHRvXFK]{stone giant's}, with two differences: its camouflage ability works in dim light instead of rocky terrain, and the \"rocks\" it hurls are composed of shadow-stuff and cause cold damage.<br>The shadow titan is friendly to you and your companions. Roll initiative for the shadow titan; it acts on its own turn. It obeys verbal or telepathic commands that you issue to it (giving a command takes no action on your part). If you don't issue any commands to the shadow titan, it defends itself from hostile creatures but otherwise takes no actions.<br>The shadow titan disappears when it drops to 0 hit points or when the spell ends.",
      "chat": "",
      "unidentified": ""
    },
    "ability": null,
    "attackBonus": 0,
    "chatFlavor": "",
    "critical": null,
    "formula": "",
    "uses": {
      "value": null,
      "max": 0,
      "per": null
    },
    "preparation": {
      "mode": "prepared",
      "prepared": false
    },
    "scaling": {
      "mode": "none",
      "formula": ""
    },
    "effects": [],
    "folder": null,
    "_stats": {
      "systemId": "dnd5e",
      "systemVersion": "2.3.1",
      "coreVersion": "11.311",
      "createdTime": 1661787234066,
      "modifiedTime": 1696391872929
    }
  },
  "sort": 0
}
