{
  "_id": "KPdraconicsmite",
  "flags": {},
  "type": "spell",
  "img": "icons/mystery-man.png",
  "name": "Draconic Smite",
  "permission": {
    "default": 0
  },
  "system": {
    "source": "DM,HH,DM:D",
    "prepared": false,
    "level": 1,
    "school": "evo",
    "activation": {
      "type": "bonus",
      "cost": "1",
      "condition": ""
    },
    "range": {
      "value": null,
      "units": "self"
    },
    "duration": {
      "value": 1,
      "units": "minute"
    },
    "components": {
      "value": "",
      "vocal": true,
      "somatic": false,
      "material": false,
      "ritual": false,
      "concentration": false
    },
    "materials": {
      "value": "",
      "consumed": false,
      "cost": 0,
      "supply": 0
    },
    "target": {
      "value": 30,
      "units": "ft",
      "type": "radius"
    },
    "actionType": "save",
    "save": {
      "ability": "con",
      "dc": null
    },
    "damage": {
      "parts": [
        [
          "1d6",
          "cold"
        ]
      ],
      "versatile": ""
    },
    "description": {
      "value": "<p><em><strong>Deep Magic: </strong>dragon</em><br>The next time you hit a creature with a melee weapon attack during the spell's duration, your weapon takes on the form of a silver dragon's head. Your attack deals an extra 1d6 cold damage, and up to four other creatures of your choosing within 30 feet of the attack's target must each make a successful Constitution saving throw or take 1d6 cold damage.<br><em><strong>At Higher Levels.</strong></em> When you cast this spell using a spell slot of 2nd level or higher, the extra cold damage and the cold damage dealt to the secondary creatures increases by 1d6 for each slot level above 1st.",
      "chat": "",
      "unidentified": ""
    },
    "ability": null,
    "attackBonus": 0,
    "chatFlavor": "",
    "critical": null,
    "formula": "",
    "uses": {
      "value": null,
      "max": 0,
      "per": null
    },
    "preparation": {
      "mode": "prepared",
      "prepared": false
    },
    "scaling": {
      "mode": "level",
      "formula": ""
    },
    "effects": [],
    "folder": null,
    "_stats": {
      "systemId": "dnd5e",
      "systemVersion": "2.3.1",
      "coreVersion": "11.311",
      "createdTime": 1661787234066,
      "modifiedTime": 1696391872929
    }
  },
  "sort": 0
}
