{
  "_id": "KPmoontrap",
  "flags": {},
  "type": "spell",
  "img": "icons/mystery-man.png",
  "name": "Moon Trap",
  "permission": {
    "default": 0
  },
  "system": {
    "source": "DM,HH",
    "prepared": false,
    "level": 4,
    "school": "abj",
    "activation": {
      "type": "hour",
      "cost": "1",
      "condition": ""
    },
    "range": {
      "value": null,
      "units": "self"
    },
    "duration": {
      "value": 8,
      "units": "hour"
    },
    "components": {
      "value": "",
      "vocal": true,
      "somatic": true,
      "material": true,
      "ritual": false,
      "concentration": false
    },
    "materials": {
      "value": "powdered silver worth 250 gp",
      "consumed": false,
      "cost": 250,
      "supply": 0
    },
    "target": {
      "value": 10,
      "units": "ft",
      "type": "square"
    },
    "actionType": "save",
    "save": {
      "ability": "wis",
      "dc": null
    },
    "damage": {
      "parts": [],
      "versatile": ""
    },
    "description": {
      "value": "<p><em><strong>Deep Magic: </strong>labyrinth</em><br>While casting this spell under the light of the moon, you inscribe a glyph that covers a 10-foot-square area on a flat, stationary surface such as a floor or a wall. Once the spell is complete, the glyph is @Compendium[dnd5e.rules.hMWCeXenROGuhF1K]{invisible} in moonlight but glows with a faint white light in darkness.<br>Any creature that touches the glyph, except those you designate during the casting of the spell, must make a successful Wisdom saving throw or be drawn into an inescapable maze until the sun rises.<br>The glyph lasts until the next sunrise, at which time it flares with bright light, and any creature trapped inside returns to the space it last occupied, unharmed. If that space has become occupied or dangerous, the creature appears in the nearest safe unoccupied space.",
      "chat": "",
      "unidentified": ""
    },
    "ability": null,
    "attackBonus": 0,
    "chatFlavor": "",
    "critical": null,
    "formula": "",
    "uses": {
      "value": null,
      "max": 0,
      "per": null
    },
    "preparation": {
      "mode": "prepared",
      "prepared": false
    },
    "scaling": {
      "mode": "none",
      "formula": ""
    },
    "effects": [],
    "folder": null,
    "_stats": {
      "systemId": "dnd5e",
      "systemVersion": "2.3.1",
      "coreVersion": "11.311",
      "createdTime": 1661787234066,
      "modifiedTime": 1696391872929
    }
  },
  "sort": 0
}
